neural_compressor/common/__init__.py
neural_compressor/common/base_config.py
neural_compressor/common/base_tuning.py
neural_compressor/common/tuning_param.py
neural_compressor/common/version.py
neural_compressor/common/utils/__init__.py
neural_compressor/common/utils/constants.py
neural_compressor/common/utils/logger.py
neural_compressor/common/utils/save_load.py
neural_compressor/common/utils/utility.py
neural_compressor/tensorflow/__init__.py
neural_compressor/tensorflow/algorithms/__init__.py
neural_compressor/tensorflow/algorithms/smoother/__init__.py
neural_compressor/tensorflow/algorithms/smoother/calibration.py
neural_compressor/tensorflow/algorithms/smoother/core.py
neural_compressor/tensorflow/algorithms/smoother/scaler.py
neural_compressor/tensorflow/algorithms/static_quant/__init__.py
neural_compressor/tensorflow/algorithms/static_quant/keras.py
neural_compressor/tensorflow/algorithms/static_quant/keras.yaml
neural_compressor/tensorflow/algorithms/static_quant/tensorflow.py
neural_compressor/tensorflow/algorithms/static_quant/tensorflow.yaml
neural_compressor/tensorflow/algorithms/static_quant/tensorflow_itex.yaml
neural_compressor/tensorflow/keras/__init__.py
neural_compressor/tensorflow/keras/layers/__init__.py
neural_compressor/tensorflow/keras/layers/conv2d.py
neural_compressor/tensorflow/keras/layers/dense.py
neural_compressor/tensorflow/keras/layers/depthwise_conv2d.py
neural_compressor/tensorflow/keras/layers/layer_initializer.py
neural_compressor/tensorflow/keras/layers/pool2d.py
neural_compressor/tensorflow/keras/layers/separable_conv2d.py
neural_compressor/tensorflow/keras/quantization/__init__.py
neural_compressor/tensorflow/keras/quantization/config.py
neural_compressor/tensorflow/quantization/__init__.py
neural_compressor/tensorflow/quantization/algorithm_entry.py
neural_compressor/tensorflow/quantization/autotune.py
neural_compressor/tensorflow/quantization/config.py
neural_compressor/tensorflow/quantization/quantize.py
neural_compressor_tf-3.7.1.dist-info/LICENSE
neural_compressor_tf-3.7.1.dist-info/METADATA
neural_compressor_tf-3.7.1.dist-info/WHEEL
neural_compressor_tf-3.7.1.dist-info/third-party-programs.txt
neural_compressor_tf-3.7.1.dist-info/top_level.txt
neural_compressor_tf-3.7.1.dist-info/RECORD
